gbmplus/__init__.py
gbmplus/config.py
gbmplus/exceptions.py
gbmplus/rest_session.py
gbmplus/api/__init__.py
gbmplus/api/accounts.py
gbmplus/api/orders.py
gbmplus/api/tradingUSA.py
gbmplus/api/transfers.py
gbmplus-0.12.dist-info/LICENSE
gbmplus-0.12.dist-info/METADATA
gbmplus-0.12.dist-info/WHEEL
gbmplus-0.12.dist-info/top_level.txt
gbmplus-0.12.dist-info/RECORD
