Metadata-Version: 2.1
Name: gbmplus
Version: 0.12
Summary: GBM Plus API Python Library
Home-page: https://github.com/markzuckerbergas/gbmplus-api-python
Author: markzuckerbergas
Author-email: markzuckerbergas@protonmail.com
License: MIT
Keywords: gbmplus,gbmhomebroker,gbm
Platform: UNKNOWN
Classifier: License :: OSI Approved :: MIT License
Classifier: Programming Language :: Python :: 3
License-File: LICENSE
Requires-Dist: requests
Requires-Dist: geocoder
